LICENSE
MANIFEST.in
README.md
setup.py
spswarehouse_airflow/__init__.py
spswarehouse_airflow/calpads.py
spswarehouse_airflow/canvas.py
spswarehouse_airflow/googledrive.py
spswarehouse_airflow/googlesheets.py
spswarehouse_airflow/googleslides.py
spswarehouse_airflow/table_names.py
spswarehouse_airflow/table_utils.py
spswarehouse_airflow/warehouse.py
spswarehouse_airflow.egg-info/PKG-INFO
spswarehouse_airflow.egg-info/SOURCES.txt
spswarehouse_airflow.egg-info/dependency_links.txt
spswarehouse_airflow.egg-info/requires.txt
spswarehouse_airflow.egg-info/top_level.txt
spswarehouse_airflow/powerschool/__init__.py
spswarehouse_airflow/powerschool/powerschool.py
spswarehouse_airflow/powerschool/powerschool_calpads.py
spswarehouse_airflow/powerschool/student_passwords.py