Metadata-Version: 2.1
Name: spswarehouse-airflow
Version: 0.5.0
Summary: Summit Public Schools Snowflake warehouse for use in Airflow
Home-page: https://github.com/SummitPublicSchools/spswarehouse_airflow
Author: Summit Public Schools; Harry Li Consulting, LLC
Author-email: warehouse@summitps.org
Classifier: Programming Language :: Python :: 3
License-File: LICENSE
